README.md
setup.py
ftredis/__init__.py
ftredis.egg-info/PKG-INFO
ftredis.egg-info/SOURCES.txt
ftredis.egg-info/dependency_links.txt
ftredis.egg-info/requires.txt
ftredis.egg-info/top_level.txt