Metadata-Version: 1.0
Name: ftredis
Version: 0.1.2
Summary: minimal wrapper for ebani module
Home-page: https://github.com/pizdoc/ftredis
Author: pizdoc
Author-email: UNKNOWN
License: UNKNOWN
Platform: UNKNOWN
